src/bcd.sv
module bcd (
    input  logic        clk,
    input  logic        rst_n,
    input  logic        iniciar,
    input  logic [15:0] binario,
    output logic [19:0] bcd_salida,
    output logic        terminado
);
    logic [35:0] registro;
    logic [4:0]  contador;
    logic        ocupado;

    always_ff @(posedge clk) begin
        logic [35:0] temp;

        if (!rst_n) begin
            terminado <= 0; ocupado <= 0; contador <= 0; registro <= 0; bcd_salida <= 0;
        end else begin
            if (iniciar && !ocupado) begin
                registro <= {20'd0, binario};
                contador <= 0;
                ocupado  <= 1;
                terminado <= 0;
            end else if (ocupado) begin
                if (contador == 16) begin
                    bcd_salida <= registro[35:16];
                    terminado  <= 1;
                    ocupado    <= 0;
                end else begin
                    // Double Dabble
                    temp = registro;
                    if (temp[19:16] >= 5) temp[19:16] += 3;
                    if (temp[23:20] >= 5) temp[23:20] += 3;
                    if (temp[27:24] >= 5) temp[27:24] += 3;
                    if (temp[31:28] >= 5) temp[31:28] += 3;
                    if (temp[35:32] >= 5) temp[35:32] += 3;

                    registro <= temp << 1;
                    contador <= contador + 1;
                end
            end
        end
    end
endmodule

TestBench/bcd_TB.sv
`timescale 1ns/1ps

module bcd_TB;
    logic clk, rst_n, iniciar, terminado;
    logic [15:0] binario;
    logic [19:0] bcd_salida;

    // Instanciamos el módulo 'bcd'
    bcd uut (
        .clk(clk), .rst_n(rst_n), .iniciar(iniciar),
        .binario(binario), .bcd_salida(bcd_salida), .terminado(terminado)
    );

    always #20 clk = ~clk;

    initial begin
        $dumpfile("build/bcd.vcd");
        $dumpvars(0, bcd_TB);

        clk = 0; rst_n = 0; iniciar = 0;
        #100 rst_n = 1;

        // Prueba 1: 255
        #40 binario = 255; iniciar = 1;
        #40 iniciar = 0;
        wait(terminado);
        #20;
        // 255 -> 0x00255 en BCD
        if (bcd_salida[11:0] == 12'h255) $display("BCD(255) PASÓ: %x", bcd_salida);
        else $error("FALLÓ BCD(255). Obtenido: %x", bcd_salida);

        $finish;
    end
endmodule

build/bcd.vcd
$date
	Sun Nov 23 21:23:42 2025
$end
$version
	Icarus Verilog
$end
$timescale
	1ps
$end
$scope module bcd_TB $end
$var wire 1 ! terminado $end
$var wire 20 " bcd_salida [19:0] $end
$var reg 16 # binario [15:0] $end
$var reg 1 $ clk $end
$var reg 1 % iniciar $end
$var reg 1 & rst_n $end
$scope module uut $end
$var wire 16 ' binario [15:0] $end
$var wire 1 $ clk $end
$var wire 1 % iniciar $end
$var wire 1 & rst_n $end
$var reg 20 ( bcd_salida [19:0] $end
$var reg 5 ) contador [4:0] $end
$var reg 1 * ocupado $end
$var reg 36 + registro [35:0] $end
$var reg 1 ! terminado $end
$scope begin $unm_blk_1 $end
$var reg 36 , temp [35:0] $end
$upscope $end
$upscope $end
$upscope $end
$enddefinitions $end
$comment Show the parameter values. $end
$dumpall
$end
#0
$dumpvars
bx ,
bx +
x*
bx )
bx (
bx '
0&
0%
0$
bx #
bx "
x!
$end
#20000
b0 "
b0 (
b0 +
b0 )
0*
0!
1$
#40000
0$
#60000
1$
#80000
0$
#100000
1$
1&
#120000
0$
#140000
1*
b11111111 +
1$
1%
b11111111 #
b11111111 '
#160000
0$
#180000
b1 )
b111111110 +
b11111111 ,
1$
0%
#200000
0$
#220000
b10 )
b1111111100 +
b111111110 ,
1$
#240000
0$
#260000
b11 )
b11111111000 +
b1111111100 ,
1$
#280000
0$
#300000
b100 )
b111111110000 +
b11111111000 ,
1$
#320000
0$
#340000
b101 )
b1111111100000 +
b111111110000 ,
1$
#360000
0$
#380000
b110 )
b11111111000000 +
b1111111100000 ,
1$
#400000
0$
#420000
b111 )
b111111110000000 +
b11111111000000 ,
1$
#440000
0$
#460000
b1000 )
b1111111100000000 +
b111111110000000 ,
1$
#480000
0$
#500000
b1001 )
b11111111000000000 +
b1111111100000000 ,
1$
#520000
0$
#540000
b1010 )
b111111110000000000 +
b11111111000000000 ,
1$
#560000
0$
#580000
b1011 )
b1111111100000000000 +
b111111110000000000 ,
1$
#600000
0$
#620000
b1100 )
b101011111000000000000 +
b10101111100000000000 ,
1$
#640000
0$
#660000
b1101 )
b1100011110000000000000 +
b110001111000000000000 ,
1$
#680000
0$
#700000
b1110 )
b11000111100000000000000 +
b1100011110000000000000 ,
1$
#720000
0$
#740000
b1111 )
b1001001111000000000000000 +
b100100111100000000000000 ,
1$
#760000
0$
#780000
b10000 )
b10010101010000000000000000 +
b1001010101000000000000000 ,
1$
#800000
0$
#820000
0*
1!
b1001010101 "
b1001010101 (
1$
